galter_subjects_utils/__init__.py
galter_subjects_utils/adapter.py
galter_subjects_utils/cli.py
galter_subjects_utils/deltor.py
galter_subjects_utils/downloader.py
galter_subjects_utils/keeptrace.py
galter_subjects_utils/reader.py
galter_subjects_utils/scheme.py
galter_subjects_utils/types_internal.py
galter_subjects_utils/updater.py
galter_subjects_utils/writer.py
galter_subjects_utils-0.8.0.dist-info/licenses/LICENSE
galter_subjects_utils-0.8.0.dist-info/METADATA
galter_subjects_utils-0.8.0.dist-info/WHEEL
galter_subjects_utils-0.8.0.dist-info/entry_points.txt
galter_subjects_utils-0.8.0.dist-info/top_level.txt
galter_subjects_utils-0.8.0.dist-info/RECORD
