Metadata-Version: 2.4
Name: galter-subjects-utils
Version: 0.8.0
Summary: Subject terms tooling for InvenioRDM
Author-email: Northwestern University <DL_FSM_GDS@e.northwestern.edu>
License: MIT License
Project-URL: Repository, https://github.com/galterlibrary/galter-subjects-utils
Keywords: invenio,inveniordm,subjects
Classifier: Environment :: Web Environment
Classifier: Intended Audience :: Developers
Classifier: License :: OSI Approved :: MIT License
Classifier: Operating System :: OS Independent
Classifier: Programming Language :: Python
Classifier: Topic :: Internet :: WWW/HTTP :: Dynamic Content
Classifier: Topic :: Software Development :: Libraries :: Python Modules
Classifier: Programming Language :: Python :: 3
Classifier: Programming Language :: Python :: 3.11
Classifier: Programming Language :: Python :: 3.12
Classifier: Programming Language :: Python :: 3.13
Requires-Python: >=3.11
License-File: LICENSE
Requires-Dist: invenio-app-rdm<14.0.0,>=12.0.0
Requires-Dist: click
Requires-Dist: flask
Requires-Dist: invenio_access
Requires-Dist: invenio_db
Requires-Dist: invenio_pidstore
Requires-Dist: invenio_rdm_records
Requires-Dist: invenio_records_resources
Requires-Dist: invenio_vocabularies
Requires-Dist: requests
Requires-Dist: sqlalchemy
Provides-Extra: dev
Requires-Dist: check-manifest>=0.49; extra == "dev"
Requires-Dist: invenio-search[opensearch2]<4.0.0,>=3.0.0; extra == "dev"
Requires-Dist: invoke<3.0,>=2.2; extra == "dev"
Requires-Dist: pytest-invenio<4.0.0,>=3.3.0; extra == "dev"
Provides-Extra: dev-pre
Requires-Dist: check-manifest>=0.49; extra == "dev-pre"
Requires-Dist: invenio-search[opensearch2]<4.0.0,>=3.0.0; extra == "dev-pre"
Requires-Dist: invoke<3.0,>=2.2; extra == "dev-pre"
Requires-Dist: pytest-invenio<4.0.0,>=3.3.0; extra == "dev-pre"
Dynamic: license-file
